pyetta/__init__.py
pyetta/__main__.py
pyetta/_builtins.py
pyetta/collectors.py
pyetta/loaders.py
pyetta/parser_data.py
pyetta/parsers.py
pyetta/reporters.py
pyetta/cli/__init__.py
pyetta/cli/cli.py
pyetta/cli/utils.py
pyetta-0.0.4.dist-info/LICENSE
pyetta-0.0.4.dist-info/METADATA
pyetta-0.0.4.dist-info/WHEEL
pyetta-0.0.4.dist-info/entry_points.txt
pyetta-0.0.4.dist-info/top_level.txt
pyetta-0.0.4.dist-info/RECORD
