Metadata-Version: 2.1
Name: pyetta
Version: 0.0.4
Summary: Tooling for automated testing on embedded bare metal platforms.
Author-email: Kenneth Ng <ngkaijie@hotmail.com>
Maintainer-email: Kenneth Ng <ngkaijie@hotmail.com>
License: MIT License
Project-URL: Repository, https://github.com/kenkaijie/pyetta
Project-URL: Documentation, https://pyetta.readthedocs.io/
Classifier: Development Status :: 1 - Planning
Classifier: Environment :: Console
Classifier: License :: OSI Approved :: MIT License
Classifier: Natural Language :: English
Classifier: Programming Language :: Python :: 3.7
Classifier: Programming Language :: Python :: 3.8
Classifier: Programming Language :: Python :: 3.9
Classifier: Programming Language :: Python :: 3.10
Classifier: Topic :: Software Development :: Embedded Systems
Classifier: Topic :: Software Development :: Testing
Classifier: Topic :: System :: Hardware
Classifier: Topic :: Utilities
Requires-Python: >=3.7
License-File: LICENSE
Requires-Dist: pyserial
Requires-Dist: click (>=8.0)
Requires-Dist: pyocd (>=0.34)
Requires-Dist: junit-xml
Requires-Dist: importlib-metadata
Provides-Extra: dev
Requires-Dist: sphinx ; extra == 'dev'
Requires-Dist: sphinx-rtd-theme ; extra == 'dev'
Requires-Dist: sphinxcontrib-mermaid ; extra == 'dev'
Requires-Dist: myst-parser ; extra == 'dev'
Requires-Dist: tomli ; extra == 'dev'
Requires-Dist: pytest (>=6.0) ; extra == 'dev'
Requires-Dist: coverage[toml] ; extra == 'dev'
Requires-Dist: flake8 ; extra == 'dev'
Requires-Dist: flake8-pyproject ; extra == 'dev'
Requires-Dist: tox (>=3.18) ; extra == 'dev'
Requires-Dist: build ; extra == 'dev'
